artl_mcp/__init__.py
artl_mcp/__main__.py
artl_mcp/_version.py
artl_mcp/cli.py
artl_mcp/client.py
artl_mcp/main.py
artl_mcp/tools.py
artl_mcp/utils/__init__.py
artl_mcp/utils/citation_utils.py
artl_mcp/utils/config_manager.py
artl_mcp/utils/conversion_utils.py
artl_mcp/utils/doi_fetcher.py
artl_mcp/utils/email_manager.py
artl_mcp/utils/file_manager.py
artl_mcp/utils/identifier_utils.py
artl_mcp/utils/pdf_fetcher.py
artl_mcp/utils/pubmed_utils.py
artl_mcp-0.33.0.dist-info/METADATA
artl_mcp-0.33.0.dist-info/WHEEL
artl_mcp-0.33.0.dist-info/entry_points.txt
artl_mcp-0.33.0.dist-info/licenses/LICENSE
artl_mcp-0.33.0.dist-info/RECORD
