Metadata-Version: 2.4
Name: artl-mcp
Version: 0.33.0
Summary: PydanticAI and MCP approaches for getting textual representations of scientific literature from PMIDs, DOIs, etc.
Project-URL: Homepage, https://github.com/contextualizer-ai/artl-mcp
Project-URL: Repository, https://github.com/contextualizer-ai/artl-mcp
Project-URL: Issues, https://github.com/contextualizer-ai/artl-mcp/issues
Project-URL: Documentation, https://github.com/contextualizer-ai/artl-mcp#readme
Author-email: Mark Andrew Miller <MAM@lbl.gov>, Justin Reese <justaddcoffee@gmail.com>
License: MIT
License-File: LICENSE
Keywords: doi,mcp,pmid,pubmed,scientific-literature
Classifier: Development Status :: 4 - Beta
Classifier: Intended Audience :: Developers
Classifier: Intended Audience :: Science/Research
Classifier: License :: OSI Approved :: MIT License
Classifier: Operating System :: OS Independent
Classifier: Programming Language :: Python :: 3
Classifier: Programming Language :: Python :: 3.11
Classifier: Programming Language :: Python :: 3.12
Classifier: Topic :: Scientific/Engineering
Classifier: Topic :: Software Development :: Libraries :: Python Modules
Requires-Python: >=3.11
Requires-Dist: beautifulsoup4>=4.9.0
Requires-Dist: fastmcp>=2.8.1
Requires-Dist: lxml>=4.6.0
Requires-Dist: markitdown>=0.1.0
Requires-Dist: pdfminer-six>=20250506
Requires-Dist: pdfplumber>=0.10.0
Requires-Dist: pydantic>=2.0.0
Requires-Dist: pyyaml>=6.0.1
Requires-Dist: requests>=2.25.0
